CONTRIBUTING.md
LICENSE
MANIFEST.in
README.md
settings.ini
setup.cfg
setup.py
hts_notebooks/hts_images/bcdd.png
hts_notebooks/hts_images/chemlib.png
hts_notebooks/hts_images/dose_response.png
hts_notebooks/hts_images/hill.png
hts_notebooks/hts_images/index_df.png
hts_notebooks/hts_images/index_heatmap.png
hts_notebooks/hts_images/layout.png
hts_notebooks/hts_images/output_13_0.png
hts_notebooks/hts_images/thalium.png
hts_notebooks/hts_images/welch.png
hts_notebooks/hts_images/xtt.png
hts_notebooks/hts_images/z.png
hts_notebooks/hts_images/z_prime.png
hts_notebooks/hts_images/z_score.png
hts_notebooks/hts_images/z_table.png
simplydrug/__init__.py
simplydrug/_nbdev.py
simplydrug/simplydrug.py
simplydrug.egg-info/PKG-INFO
simplydrug.egg-info/SOURCES.txt
simplydrug.egg-info/dependency_links.txt
simplydrug.egg-info/entry_points.txt
simplydrug.egg-info/not-zip-safe
simplydrug.egg-info/requires.txt
simplydrug.egg-info/top_level.txt