Metadata-Version: 2.1
Name: simplydrug
Version: 0.0.4
Summary: tutorials and scripts for drug discovery
Home-page: https://github.com/disc04/simplydrug
Author: Anastasia Abashidze
Author-email: abashidze.anastasia@gmail.com
License: Apache Software License 2.0
Download-URL: https://github.com/disc04/simplydrug/archive/v0.0.4.tar.gz
Keywords: drug discovery tutorial python
Platform: UNKNOWN
Classifier: Development Status :: 3 - Alpha
Classifier: Intended Audience :: Developers
Classifier: License :: OSI Approved :: Apache Software License
Classifier: Natural Language :: English
Classifier: Programming Language :: Python :: 3.6
Classifier: Programming Language :: Python :: 3.7
Classifier: Programming Language :: Python :: 3.8
Requires-Python: >=3.6
